streamlit_vis_network/__init__.py
streamlit_vis_network/frontend/build/asset-manifest.json
streamlit_vis_network/frontend/build/bootsrap.min.css
streamlit_vis_network/frontend/build/index.html
streamlit_vis_network/frontend/build/static/js/main.249804f0.js
streamlit_vis_network/frontend/build/static/js/main.249804f0.js.LICENSE.txt
streamlit_vis_network/frontend/build/static/js/main.249804f0.js.map
streamlit_vis_network/frontend/build/static/js/main.f827116b.js
streamlit_vis_network/frontend/build/static/js/main.f827116b.js.LICENSE.txt
streamlit_vis_network/frontend/build/static/js/main.f827116b.js.map
streamlit_vis_network-0.1.3.dist-info/LICENSE
streamlit_vis_network-0.1.3.dist-info/METADATA
streamlit_vis_network-0.1.3.dist-info/WHEEL
streamlit_vis_network-0.1.3.dist-info/top_level.txt
streamlit_vis_network-0.1.3.dist-info/RECORD
