Metadata-Version: 2.2
Name: streamlit-vis-network
Version: 0.1.3
Summary: Network graph visualization in Streamlit using vis.js
Home-page: https://github.com/q-maze/streamlit-vis-network
Author: Q
Author-email: qmazedev@gmail.com
Requires-Python: >=3.7
License-File: LICENSE
Requires-Dist: setuptools>=75.8.0
Requires-Dist: streamlit>=1.41.1
Requires-Dist: twine>=6.0.1
Dynamic: author
Dynamic: author-email
Dynamic: home-page
Dynamic: requires-python
